{
  "Andaman_&_Nicobar_Islands": [
    "Andaman & Nicobar Islands"
  ],
  "Andhra_Pradesh": [
    "Adilabad",
    "Amalapuram",
    "Anakapalli",
    "Anantapur",
    "Aruku",
    "Bapatla",
    "Bhadrachalam",
    "Bhongir",
    "Bobbili",
    "Chelvella",
    "Chittoor",
    "Cuddapah",
    "Eluru",
    "Guntur",
    "Hanamkonda",
    "Hindupur",
    "Hyderabad",
    "Kadapa",
    "Kakinada",
    "Karimnagar",
    "Khammam",
    "Kurnool",
    "Machilipatnam",
    "Mahabubabad",
    "Mahabubnagar",
    "Mahbubnagar",
    "Malkajgiri",
    "Medak",
    "Miryalguda",
    "Nagarkurnool",
    "Nalgonda",
    "Nandyal",
    "Narasapur",
    "Narasaraopet",
    "Narsapuram",
    "Nellore",
    "Nizamabad",
    "Ongole",
    "Parvathipuram",
    "Peddapalle",
    "Peddapalli",
    "Rajahmundry",
    "Rajampet",
    "Secunderabad",
    "Secundrabad",
    "Siddipet",
    "Srikakulam",
    "Tenali",
    "Tirupathi",
    "Tirupati",
    "Vijayawada",
    "Visakhapatnam",
    "Vizianagaram",
    "Warangal",
    "Zahirabad"
  ],
  "Arunachal_Pradesh": [
    "Arunachal East",
    "Arunachal West"
  ],
  "Assam": [
    "Autonomous District",
    "Barpeta",
    "Dhubri",
    "Dibrugarh",
    "Gauhati",
    "Jorhat",
    "Kaliabor",
    "Karimganj",
    "Kokrajhar",
    "Lakhimpur",
    "Mangaldoi",
    "Nowgong",
    "Silchar",
    "Tezpur"
  ],
  "Bihar": [
    "Araria",
    "Arrah",
    "Aurangabad",
    "Bagaha",
    "Balia",
    "Banka",
    "Barh",
    "Begusarai",
    "Bettiah",
    "Bhagalpur",
    "Bikramganj",
    "Buxar",
    "Chapra",
    "Chatra",
    "Darbhanga",
    "Dhanbad",
    "Dumka",
    "Gaya",
    "Gaya (Sc)",
    "Giridih",
    "Godda",
    "Gopalganj",
    "Gopalganj (Sc)",
    "Hajipur",
    "Hajipur (Sc)",
    "Hazaribagh",
    "Jahanabad",
    "Jamshedpur",
    "Jamui",
    "Jamui (Sc)",
    "Jhanjharpur",
    "Karakat",
    "Katihar",
    "Khagaria",
    "Khunti",
    "Kishanganj",
    "Kodarma",
    "Lohardaga",
    "Madhepura",
    "Madhubani",
    "Maharajganj",
    "Monghyr",
    "Motihari",
    "Munger",
    "Muzaffarpur",
    "Nalanda",
    "Nawada",
    "Palamau",
    "Palamu",
    "Paschim Champaran",
    "Pataliputra",
    "Patna",
    "Patna Sahib",
    "Purnea",
    "Purnia",
    "Purvi Champaran",
    "Rajmahal",
    "Ranchi",
    "Rosera",
    "Saharsa",
    "Samastipur",
    "Samastipur (Sc)",
    "Saran",
    "Sasaram",
    "Sasaram (Sc)",
    "Sheohar",
    "Singhbhum",
    "Sitamarhi",
    "Siwan",
    "Supaul",
    "Ujiarpur",
    "Vaishali",
    "Valmiki Nagar"
  ],
  "Chandigarh": [
    "Chandigarh"
  ],
  "Chhattisgarh": [
    "Bastar",
    "Bilaspur",
    "Durg",
    "Janjgir",
    "Janjgir-Champa",
    "Kanker",
    "Korba",
    "Mahasamund",
    "Raigarh",
    "Raipur",
    "Rajnandgaon",
    "Sarangarh",
    "Sarguja",
    "Surguja"
  ],
  "Dadra_&_Nagar_Haveli": [
    "Dadar & Nagar Haveli",
    "Dadra & Nagar Haveli",
    "Dadra And Nagar Haveli"
  ],
  "Daman_&_Diu": [
    "Daman & Diu",
    "Daman And Diu"
  ],
  "Delhi": [
    "Chandni Chowk",
    "Delhi Sadar",
    "East Delhi",
    "Karol Bagh",
    "New Delhi",
    "North East Delhi",
    "North West  Delhi",
    "North West Delhi",
    "Outer Delhi",
    "South Delhi",
    "West  Delhi",
    "West Delhi"
  ],
  "Goa": [
    "Mormugao",
    "North Goa",
    "Panaji",
    "South Goa"
  ],
  "Gujarat": [
    "Ahmedabad",
    "Ahmedabad East",
    "Ahmedabad West",
    "Amreli",
    "Anand",
    "Banaskantha",
    "Bardoli",
    "Baroda",
    "Bharuch",
    "Bhavnagar",
    "Broach",
    "Bulsar",
    "Chhota Udaipur",
    "Dahod",
    "Dhandhuka",
    "Dohad",
    "Gandhinagar",
    "Godhra",
    "Jamnagar",
    "Junagadh",
    "Kachchh",
    "Kaira",
    "Kapadvanj",
    "Kheda",
    "Kutch",
    "Mahesana",
    "Mandvi",
    "Mehsana",
    "Navsari",
    "Panchmahal",
    "Patan",
    "Porbandar",
    "Rajkot",
    "Sabarkantha",
    "Surat",
    "Surendranagar",
    "Vadodara",
    "Valsad"
  ],
  "Haryana": [
    "Ambala",
    "Bhiwani",
    "Bhiwani-Mahendragarh",
    "Faridabad",
    "Gurgaon",
    "Hisar",
    "Hissar",
    "Karnal",
    "Kurukshetra",
    "Mahendragarh",
    "Rohtak",
    "Sirsa",
    "Sonepat",
    "Sonipat"
  ],
  "Himachal_Pradesh": [
    "Hamirpur",
    "Kangra",
    "Mandi",
    "Shimla",
    "Simla"
  ],
  "Jammu_&_Kashmir": [
    "Anantnag",
    "Baramulla",
    "Jammu",
    "Ladakh",
    "Srinagar",
    "Udhampur"
  ],
  "Jharkhand": [
    "Chatra",
    "Dhanbad",
    "Dumka",
    "Giridih",
    "Godda",
    "Hazaribagh",
    "Jamshedpur",
    "Khunti",
    "Kodarma",
    "Lohardaga",
    "Palamau",
    "Rajmahal",
    "Ranchi",
    "Singhbhum"
  ],
  "Karnataka": [
    "Bagalkot",
    "Bangalore Central",
    "Bangalore North",
    "Bangalore Rural",
    "Bangalore South",
    "Belgaum",
    "Bellary",
    "Bidar",
    "Bijapur",
    "Chamarajanagar",
    "Chikballapur",
    "Chikkballapur",
    "Chikkodi",
    "Chikmagalur",
    "Chitradurga",
    "Dakshina Kannada",
    "Davanagere",
    "Davangere",
    "Dharwad",
    "Dharwad North",
    "Dharwad South",
    "Gulbarga",
    "Hassan",
    "Haveri",
    "Kanakapura",
    "Kanara",
    "Kolar",
    "Koppal",
    "Mandya",
    "Mangalore",
    "Mysore",
    "Raichur",
    "Shimoga",
    "Tumkur",
    "Udupi",
    "Udupi Chikmagalur",
    "Uttara Kannada"
  ],
  "Kerala": [
    "Adoor",
    "Alappuzha",
    "Alathur",
    "Alleppey",
    "Attingal",
    "Badagara",
    "Calicut",
    "Cannanore",
    "Chalakudy",
    "Chirayinkil",
    "Ernakulam",
    "Idukki",
    "Kannur",
    "Kasaragod",
    "Kollam",
    "Kottayam",
    "Kozhikode",
    "Malappuram",
    "Manjeri",
    "Mavelikara",
    "Mavelikkara",
    "Mukundapuram",
    "Muvattupuzha",
    "Ottapalam",
    "Palakkad",
    "Palghat",
    "Pathanamthitta",
    "Ponnani",
    "Quilon",
    "Thiruvananthapuram",
    "Thrissur",
    "Trichur",
    "Trivandrum",
    "Vadakara",
    "Wayanad"
  ],
  "Lakshadweep": [
    "Lakshadweep"
  ],
  "Madhya_Pradesh": [
    "Balaghat",
    "Bastar",
    "Betul",
    "Bhind",
    "Bhopal",
    "Bilaspur",
    "Chhindwara",
    "Damoh",
    "Dewas",
    "Dhar",
    "Durg",
    "Guna",
    "Gwalior",
    "Hoshangabad",
    "Indore",
    "Jabalpur",
    "Janjgir",
    "Jhabua",
    "Kanker",
    "Khajuraho",
    "Khandwa",
    "Khargone",
    "Mahasamund",
    "Mandla",
    "Mandsaur",
    "Mandsour",
    "Morena",
    "Raigarh",
    "Raipur",
    "Rajgarh",
    "Rajnandgaon",
    "Ratlam",
    "Rewa",
    "Sagar",
    "Sarangarh",
    "Satna",
    "Seoni",
    "Shahdol",
    "Shajapur",
    "Sidhi",
    "Surguja",
    "Tikamgarh",
    "Ujjain",
    "Vidisha"
  ],
  "Maharashtra": [
    "Ahmadnagar",
    "Ahmednagar",
    "Akola",
    "Amravati",
    "Aurangabad",
    "Baramati",
    "Beed",
    "Bhandara",
    "Bhandara - Gondiya",
    "Bhiwandi",
    "Bombay North",
    "Bombay North Central",
    "Bombay North East",
    "Bombay North West",
    "Bombay South",
    "Bombay South Central",
    "Buldhana",
    "Chandrapur",
    "Chimur",
    "Dahanu",
    "Dhule",
    "Dindori",
    "Erandol",
    "Gadchiroli-Chimur",
    "Hatkanangle",
    "Hingoli",
    "Ichalkaranji",
    "Jalgaon",
    "Jalna",
    "Kalyan",
    "Karad",
    "Khed",
    "Kolaba",
    "Kolhapur",
    "Kopargaon",
    "Latur",
    "Madha",
    "Malegaon",
    "Maval",
    "Mumbai   South",
    "Mumbai North",
    "Mumbai North Central",
    "Mumbai North East",
    "Mumbai North West",
    "Mumbai South",
    "Mumbai South Central",
    "Nagpur",
    "Nanded",
    "Nandurbar",
    "Nashik",
    "Osmanabad",
    "Palghar",
    "Pandharpur",
    "Parbhani",
    "Pune",
    "Raigad",
    "Rajapur",
    "Ramtek",
    "Ratnagiri",
    "Ratnagiri - Sindhudurg",
    "Raver",
    "Sangli",
    "Satara",
    "Shirdi",
    "Shirur",
    "Sholapur",
    "Solapur",
    "Thane",
    "Wardha",
    "Washim",
    "Yavatmal",
    "Yavatmal-Washim"
  ],
  "Manipur": [
    "Inner Manipur",
    "Outer Manipur"
  ],
  "Meghalaya": [
    "Shillong",
    "Tura"
  ],
  "Mizoram": [
    "Mizoram"
  ],
  "Nagaland": [
    "Nagaland"
  ],
  "Odisha": [
    "Aska",
    "Balasore",
    "Bargarh",
    "Berhampur",
    "Bhadrak",
    "Bhubaneswar",
    "Bolangir",
    "Cuttack",
    "Deogarh",
    "Dhenkanal",
    "Jagatsinghpur",
    "Jajpur",
    "Kalahandi",
    "Kandhamal",
    "Kendrapara",
    "Keonjhar",
    "Koraput",
    "Mayurbhanj",
    "Nabarangpur",
    "Nowrangpur",
    "Phulbani",
    "Puri",
    "Sambalpur",
    "Sundargarh"
  ],
  "Puducherry": [
    "Pondicherry",
    "Puducherry"
  ],
  "Punjab": [
    "Amritsar",
    "Anandpur Sahib",
    "Bathinda",
    "Bhatinda",
    "Faridkot",
    "Fatehgarh Sahib",
    "Ferozepur",
    "Ferozpur",
    "Firozpur",
    "Gurdaspur",
    "Hoshiarpur",
    "Jalandhar",
    "Jullundur",
    "Khadoor Sahib",
    "Ludhiana",
    "Patiala",
    "Phillaur",
    "Ropar",
    "Sangrur",
    "Tarn Taran",
    "Tarntaran"
  ],
  "Rajasthan": [
    "Ajmer",
    "Alwar",
    "Banswara",
    "Barmer",
    "Bayana",
    "Bharatpur",
    "Bhilwara",
    "Bikaner",
    "Bikaner (Sc)",
    "Chittorgarh",
    "Churu",
    "Dausa",
    "Ganganagar",
    "Jaipur",
    "Jaipur Rural",
    "Jalore",
    "Jhalawar",
    "Jhalawar-Baran",
    "Jhunjhunu",
    "Jodhpur",
    "Karauli-Dholpur",
    "Kota",
    "Nagaur",
    "Pali",
    "Rajsamand",
    "Salumber",
    "Sawai Madhopur",
    "Sikar",
    "Tonk",
    "Tonk-Sawai Madhopur",
    "Udaipur"
  ],
  "Sikkim": [
    "Sikkim"
  ],
  "Tamil_Nadu": [
    "Arakkonam",
    "Arani",
    "Chengalpattu",
    "Chennai Central",
    "Chennai North",
    "Chennai South",
    "Chidambaram",
    "Coimbatore",
    "Cuddalore",
    "Dharmapuri",
    "Dindigul",
    "Erode",
    "Gobichettipalayam",
    "Kallakurichi",
    "Kancheepuram",
    "Kanniyakumari",
    "Karur",
    "Krishnagiri",
    "Madras Central",
    "Madras North",
    "Madras South",
    "Madurai",
    "Mayiladuthurai",
    "Mayiladuturai",
    "Nagapattinam",
    "Nagercoil",
    "Namakkal",
    "Nilgiris",
    "Palani",
    "Perambalur",
    "Periyakulam",
    "Pollachi",
    "Pudukkottai",
    "Ramanathapuram",
    "Rasipuram",
    "Salem",
    "Sivaganga",
    "Sivakasi",
    "Sriperumbudur",
    "Tenkasi",
    "Thanjavur",
    "Theni",
    "Thiruvallur",
    "Thoothukkudi",
    "Tindivanam",
    "Tiruchendur",
    "Tiruchengode",
    "Tiruchirappalli",
    "Tirunelveli",
    "Tiruppattur",
    "Tiruppur",
    "Tiruvannamalai",
    "Vandavasi",
    "Vellore",
    "Viluppuram",
    "Virudhunagar"
  ],
  "Telangana": [
    "Adilabad",
    "Bhongir",
    "Chevella",
    "Hyderabad",
    "Karimnagar",
    "Khammam",
    "Mahabubabad",
    "Mahbubnagar",
    "Malkajgiri",
    "Medak",
    "Nagarkurnool",
    "Nalgonda",
    "Nizamabad",
    "Peddapalle",
    "Secundrabad",
    "Warangal",
    "Zahirabad"
  ],
  "Tripura": [
    "Tripura East",
    "Tripura West"
  ],
  "Uttar_Pradesh": [
    "Agra",
    "Akbarpur",
    "Aligarh",
    "Allahabad",
    "Almora",
    "Ambedkar Nagar",
    "Amethi",
    "Amroha",
    "Aonla",
    "Azamgarh",
    "Badaun",
    "Baghpat",
    "Bahraich",
    "Ballia",
    "Balrampur",
    "Banda",
    "Bansgaon",
    "Bara Banki",
    "Barabanki",
    "Bareilly",
    "Basti",
    "Bhadohi",
    "Bijnor",
    "Bilhaur",
    "Budaun",
    "Bulandshahr",
    "Chail",
    "Chandauli",
    "Deoria",
    "Dhaurahra",
    "Domariaganj",
    "Domariyaganj",
    "Etah",
    "Etawah",
    "Faizabad",
    "Farrukhabad",
    "Fatehpur",
    "Fatehpur Sikri",
    "Firozabad",
    "Garhwal",
    "Gautam Buddh Nagar",
    "Gautam Buddha Nagar",
    "Ghatampur",
    "Ghaziabad",
    "Ghazipur",
    "Ghosi",
    "Gonda",
    "Gorakhpur",
    "Hamirpur",
    "Hapur",
    "Hardoi",
    "Hardwar",
    "Hathras",
    "Jalaun",
    "Jalesar",
    "Jaunpur",
    "Jhansi",
    "Kairana",
    "Kaiserganj",
    "Kannauj",
    "Kanpur",
    "Kaushambi",
    "Khalilabad",
    "Kheri",
    "Khurja",
    "Kushi Nagar",
    "Lalganj",
    "Lucknow",
    "Machhlishahr",
    "Maharajganj",
    "Mainpuri",
    "Mainpuri(Gen)",
    "Mathura",
    "Meerut",
    "Mirzapur",
    "Misrikh",
    "Mohanlalganj",
    "Moradabad",
    "Muzaffarnagar",
    "Nagina",
    "Nainital",
    "Padrauna",
    "Phulpur",
    "Pilibhit",
    "Pratapgarh",
    "Rae Bareli",
    "Rampur",
    "Robertsganj",
    "Saharanpur",
    "Saidpur",
    "Salempur",
    "Sambhal",
    "Sant Kabir Nagar",
    "Shahabad",
    "Shahjahanpur",
    "Shrawasti",
    "Sitapur",
    "Sultanpur",
    "Tehri Garhwal",
    "Unnao",
    "Varanasi"
  ],
  "Uttarakhand": [
    "Almora",
    "Garhwal",
    "Hardwar",
    "Nainital",
    "Nainital-Udhamsingh Nagar",
    "Tehri Garhwal"
  ],
  "West_Bengal": [
    "Alipurduars",
    "Arambagh",
    "Asansol",
    "Baharampur",
    "Balurghat",
    "Bangaon",
    "Bankura",
    "Barasat",
    "Bardhaman Durgapur",
    "Bardhaman Purba",
    "Barrackpore",
    "Basirhat",
    "Berhampore",
    "Birbhum",
    "Bishnupur",
    "Bolpur",
    "Burdwan",
    "Burdwan - Durgapur",
    "Calcutta North East",
    "Calcutta North West",
    "Calcutta South",
    "Contai",
    "Cooch Behar",
    "Darjeeling",
    "Diamond Harbour",
    "Dum Dum",
    "Durgapur",
    "Ghatal",
    "Hooghly",
    "Howrah",
    "Jadavpur",
    "Jalpaiguri",
    "Jangipur",
    "Jaynagar",
    "Jhargram",
    "Joynagar",
    "Kanthi",
    "Katwa",
    "Kolkata Dakshin",
    "Kolkata Uttar",
    "Krishnagar",
    "Krishnanagar",
    "Malda",
    "Maldaha Dakshin",
    "Maldaha Uttar",
    "Mathurapur",
    "Medinipur",
    "Midnapore",
    "Murshidabad",
    "Nabadwip",
    "Panskura",
    "Purulia",
    "Raiganj",
    "Ranaghat",
    "Serampore",
    "Srerampur",
    "Tamluk",
    "Uluberia",
    "Vishnupur"
  ]
}